docker_cli/__init__.py
docker_cli/cli.py
docker_cli/docker_logic/__init__.py
docker_cli/docker_logic/cli_functions/__init__.py
docker_cli/docker_logic/cli_functions/builder.py
docker_cli/docker_logic/cli_functions/runner.py
docker_cli/docker_logic/cli_functions/util.py
docker_cli/docker_logic/conf_files/__init__.py
docker_cli/docker_logic/conf_files/config_git_user.sh
docker_cli/docker_logic/conf_files/fetch_ssh_public_keys.sh
docker_cli/docker_logic/conf_files/ldap.conf
docker_cli/docker_logic/conf_files/libnss-ldap.conf
docker_cli/docker_logic/conf_files/pam_ldap.conf
docker_cli/docker_logic/conf_files/pam_mkhomedir.conf
docker_cli/docker_logic/conf_files/ruff_pre-commit-config.yaml
docker_cli/docker_logic/conf_files/supervisord.conf
docker_cli/docker_logic/conf_files/test.py
docker_cli/docker_logic/scripts/__init__.py
docker_cli/docker_logic/scripts/init_precommit.sh
docker_cli/docker_logic/scripts/test.py
docker_cli/docker_logic/templates/Dockerfile.j2
docker_cli/docker_logic/templates/__init__.py
pby_cli-0.1.1.dist-info/METADATA
pby_cli-0.1.1.dist-info/WHEEL
pby_cli-0.1.1.dist-info/entry_points.txt
pby_cli-0.1.1.dist-info/top_level.txt
pby_cli-0.1.1.dist-info/RECORD
