Metadata-Version: 2.4
Name: pby-cli
Version: 0.1.1
Summary: CLI pour gérer les images et conteneurs Docker Probayes
Requires-Python: >=3.8
Requires-Dist: typer[all]
Requires-Dist: jinja2
